notebookx/__init__.py
notebookx/__init__.pyi
notebookx/_notebookx.pypy39-pp73-aarch64-linux-gnu.so
notebookx/cli.py
notebookx/py.typed
notebookx_py-0.1.1.dist-info/METADATA
notebookx_py-0.1.1.dist-info/WHEEL
notebookx_py-0.1.1.dist-info/entry_points.txt
notebookx_py-0.1.1.dist-info/RECORD
