Metadata-Version: 2.4
Name: notebookx-py
Version: 0.1.1
Classifier: Development Status :: 3 - Alpha
Classifier: Intended Audience :: Developers
Classifier: License :: OSI Approved :: MIT License
Classifier: Programming Language :: Python :: 3
Classifier: Programming Language :: Python :: 3.8
Classifier: Programming Language :: Python :: 3.9
Classifier: Programming Language :: Python :: 3.10
Classifier: Programming Language :: Python :: 3.11
Classifier: Programming Language :: Python :: 3.12
Classifier: Programming Language :: Rust
Classifier: Topic :: Software Development :: Libraries
Requires-Dist: pytest>=7.0 ; extra == 'dev'
Requires-Dist: mypy>=1.0 ; extra == 'dev'
Provides-Extra: dev
Summary: Fast, lightweight notebook conversion library
Keywords: jupyter,notebook,conversion,ipynb
License: MIT
Requires-Python: >=3.8
Project-URL: Homepage, https://github.com/lukastk/notebookx
Project-URL: Repository, https://github.com/lukastk/notebookx
